pyseedmip/libSeedMIP.so.0
pyseedmip/__init__.py
pyseedmip/pyseedmip.pyi
pyseedmip/libSeedMIP.so
pyseedmip/__init__.pyi
pyseedmip/libSeedMIP.so.0.1.0
pyseedmip/pyseedmip.cpython-310-x86_64-linux-gnu.so
pyseedmip-0.2.2.dist-info/WHEEL
pyseedmip-0.2.2.dist-info/METADATA
pyseedmip-0.2.2.dist-info/RECORD
