Metadata-Version: 2.1
Name: pyseedmip
Version: 0.2.2
Summary: SeedMIP for Python
Author-Email: SeedMath <dev@seedmath.com>
Classifier: Development Status :: 4 - Beta
Classifier: License :: OSI Approved :: MIT License
Classifier: Programming Language :: Python :: 3 :: Only
Classifier: Programming Language :: Python :: 3.7
Classifier: Programming Language :: Python :: 3.8
Classifier: Programming Language :: Python :: 3.9
Classifier: Programming Language :: Python :: 3.10
Classifier: Programming Language :: Python :: 3.11
Classifier: Programming Language :: Python :: 3.12
Classifier: Programming Language :: Python :: 3.13
Requires-Python: >=3.9
Requires-Dist: seedkey>=0.2.21
Provides-Extra: test
Requires-Dist: pytest; extra == "test"
